helloworld.py
tusmehta_helloworld-0.0.4.dist-info/LICENSE.txt
tusmehta_helloworld-0.0.4.dist-info/METADATA
tusmehta_helloworld-0.0.4.dist-info/WHEEL
tusmehta_helloworld-0.0.4.dist-info/top_level.txt
tusmehta_helloworld-0.0.4.dist-info/RECORD
