Metadata-Version: 2.1
Name: tusmehta-helloworld
Version: 0.0.4
Summary: Say Hello!
Home-page: https://github.com/TusharMehtani/tusmehta-helloworld
Author: Tushar Mehtani
Author-email: tushar.mehtani@publicissapient.com
License: UNKNOWN
Platform: UNKNOWN
Classifier: License :: OSI Approved :: MIT License
Classifier: Operating System :: OS Independent
Classifier: Programming Language :: Python :: 3
Classifier: Programming Language :: Python :: 3.6
Classifier: Programming Language :: Python :: 3.7
Requires-Dist: blessings (~=1.7)
Provides-Extra: dev
Requires-Dist: pytest (>=3.7) ; extra == 'dev'
